{
  "id": "7f80d8ac-a725-4cd6-935d-57528e95edb6",
  "name": "container7",
  "type": "Container",
  "pageId": "cf8f3631-503b-4941-b5c1-d489b6343752",
  "parent": "da08124a-a919-40fe-8c3a-8e988105d5d6",
  "properties": {
    "showHeader": {
      "value": false
    },
    "loadingState": {
      "value": "{{false}}"
    },
    "visibility": {
      "value": "{{true}}"
    },
    "disabledState": {
      "value": "{{false}}"
    },
    "dynamicHeight": {
      "value": "{{true}}"
    },
    "headerHeight": {
      "value": "{{80}}"
    },
    "canvasHeight": {
      "value": 34
    }
  },
  "general": {},
  "styles": {
    "backgroundColor": {
      "value": "var(--cc-surface1-surface)"
    },
    "headerBackgroundColor": {
      "value": "var(--cc-surface1-surface)"
    },
    "borderRadius": {
      "value": "6"
    },
    "borderColor": {
      "value": "var(--cc-default-border)"
    },
    "boxShadow": {
      "value": "0px 0px 0px 0px #00000040"
    },
    "headerDividerColor": {
      "value": "var(--cc-default-border)"
    }
  },
  "generalStyles": {
    "box_shadow": {
      "value": "0px 0px 0px 0px #00000040"
    }
  },
  "displayPreferences": {
    "show_on_desktop": {
      "value": "{{true}}"
    },
    "show_on_mobile": {
      "value": "{{false}}"
    },
    "showOnDesktop": {
      "value": "{{true}}"
    },
    "showOnMobile": {
      "value": "{{false}}"
    }
  },
  "validation": {},
  "layouts": [
    {
      "id": "64792e5c-2ddb-420a-a638-ff65349e3e49",
      "type": "desktop",
      "top": 20,
      "left": 1,
      "width": 41,
      "height": 60,
      "componentId": "7f80d8ac-a725-4cd6-935d-57528e95edb6",
      "dimensionUnit": "count"
    },
    {
      "id": "a58157fc-96c1-4c5a-a576-ae777b003990",
      "type": "mobile",
      "top": 0,
      "left": 0,
      "width": 0,
      "height": 0,
      "componentId": "7f80d8ac-a725-4cd6-935d-57528e95edb6",
      "dimensionUnit": "count"
    }
  ]
}