{
  "id": "90ad82ec-182f-4b58-95d5-7b05bfee116e",
  "name": "completeRolloutContainer",
  "type": "Container",
  "pageId": "cf8f3631-503b-4941-b5c1-d489b6343752",
  "parent": "5d99b12a-a84e-4f90-886b-a3f89633b93f-t3",
  "properties": {
    "showHeader": {
      "value": "{{false}}"
    },
    "loadingState": {
      "value": "{{queries.242b72d0-2f1f-4719-b85c-9f698cefeefb.isLoading}}",
      "fxActive": true
    },
    "visibility": {
      "value": "{{true}}"
    },
    "disabledState": {
      "value": "{{false}}"
    },
    "dynamicHeight": {
      "value": "{{false}}"
    },
    "headerHeight": {
      "value": "{{80}}"
    }
  },
  "general": {},
  "styles": {
    "backgroundColor": {
      "value": "var(--cc-surface1-surface)"
    },
    "headerBackgroundColor": {
      "value": "var(--cc-surface1-surface)"
    },
    "headerDividerColor": {
      "value": "var(--cc-default-border)"
    },
    "borderRadius": {
      "value": "6"
    },
    "borderColor": {
      "value": "var(--cc-weak-border)"
    },
    "boxShadow": {
      "value": "0px 0px 0px 0px #00000040"
    }
  },
  "generalStyles": {},
  "displayPreferences": {
    "showOnDesktop": {
      "value": "{{true}}"
    },
    "showOnMobile": {
      "value": "{{false}}"
    }
  },
  "validation": {},
  "layouts": [
    {
      "id": "a2dff5bc-4cd0-45a3-bc61-4128956412df",
      "type": "desktop",
      "top": 20,
      "left": 3,
      "width": 37,
      "height": 450,
      "componentId": "90ad82ec-182f-4b58-95d5-7b05bfee116e",
      "dimensionUnit": "count"
    },
    {
      "id": "933b7382-b129-45ec-9391-58769ad2acee",
      "type": "mobile",
      "top": 50,
      "left": 11,
      "width": 23,
      "height": 450,
      "componentId": "90ad82ec-182f-4b58-95d5-7b05bfee116e",
      "dimensionUnit": "count"
    }
  ]
}