{
  "id": "d7868750-ede5-402c-aa57-24f2269227f3",
  "name": "container72",
  "type": "Container",
  "pageId": "cf8f3631-503b-4941-b5c1-d489b6343752",
  "parent": "ff74fde0-903f-41f0-9063-213741008261-t12",
  "properties": {
    "showHeader": {
      "value": true
    },
    "loadingState": {
      "value": "{{false}}"
    },
    "visibility": {
      "value": "{{true}}"
    },
    "disabledState": {
      "value": "{{false}}"
    },
    "dynamicHeight": {
      "value": "{{false}}"
    },
    "headerHeight": {
      "value": "{{80}}"
    }
  },
  "general": {},
  "styles": {
    "backgroundColor": {
      "value": "var(--cc-surface1-surface)"
    },
    "headerBackgroundColor": {
      "value": "var(--cc-surface1-surface)"
    },
    "headerDividerColor": {
      "value": "var(--cc-default-border)"
    },
    "borderRadius": {
      "value": "6"
    },
    "borderColor": {
      "value": "var(--cc-default-border)"
    },
    "boxShadow": {
      "value": "0px 0px 0px 0px #00000040"
    }
  },
  "generalStyles": {
    "box_shadow": {
      "value": "0px 0px 0px 0px #00000040"
    }
  },
  "displayPreferences": {
    "showOnDesktop": {
      "value": "{{true}}"
    },
    "showOnMobile": {
      "value": "{{false}}"
    },
    "show_on_desktop": {
      "value": "{{true}}"
    },
    "show_on_mobile": {
      "value": "{{false}}"
    }
  },
  "validation": {},
  "layouts": [
    {
      "id": "a12b5b41-72ff-4128-b082-dadc99896b7f",
      "type": "desktop",
      "top": 0,
      "left": 0,
      "width": null,
      "height": 8,
      "componentId": "d7868750-ede5-402c-aa57-24f2269227f3",
      "dimensionUnit": "count"
    },
    {
      "id": "ee6c9cd6-d443-4c6e-90eb-9c1b8ebb14f4",
      "type": "mobile",
      "top": 0,
      "left": 0,
      "width": 0,
      "height": 0,
      "componentId": "d7868750-ede5-402c-aa57-24f2269227f3",
      "dimensionUnit": "count"
    }
  ]
}