{
  "id": "dc252ecb-1a7c-4f71-b87e-131ccb40c750",
  "name": "text256",
  "type": "Text",
  "pageId": "cf8f3631-503b-4941-b5c1-d489b6343752",
  "parent": "e8044432-a0a8-4cb2-900d-131e0fe4e0bb",
  "properties": {
    "textFormat": {
      "value": "markdown"
    },
    "dynamicHeight": {
      "value": "{{false}}"
    },
    "text": {
      "value": "**Marketplace ID: {{marketplaceKeyValueObj.value.LEGACY_MARKETPLACE_ID}}**"
    },
    "loadingState": {
      "value": "{{false}}"
    },
    "disabledState": {
      "value": "{{false}}"
    },
    "visibility": {
      "value": "{{true}}"
    }
  },
  "general": {},
  "styles": {
    "backgroundColor": {
      "value": "#fff00000"
    },
    "textColor": {
      "value": "var(--cc-primary-text)"
    },
    "textSize": {
      "value": "{{14}}"
    },
    "textAlign": {
      "value": "left"
    },
    "fontWeight": {
      "value": "normal"
    },
    "decoration": {
      "value": "none"
    },
    "transformation": {
      "value": "none"
    },
    "fontStyle": {
      "value": "normal"
    },
    "lineHeight": {
      "value": "{{1.5}}"
    },
    "textIndent": {
      "value": "{{0}}"
    },
    "letterSpacing": {
      "value": "{{0}}"
    },
    "wordSpacing": {
      "value": "{{0}}"
    },
    "fontVariant": {
      "value": "normal"
    },
    "verticalAlignment": {
      "value": "center"
    },
    "padding": {
      "value": "default"
    },
    "boxShadow": {
      "value": "0px 0px 0px 0px #00000040"
    },
    "borderColor": {
      "value": "#ffffff00"
    },
    "borderRadius": {
      "value": "{{6}}"
    },
    "isScrollRequired": {
      "value": "enabled"
    }
  },
  "generalStyles": {
    "box_shadow": {
      "value": "0px 0px 0px 0px #00000040"
    }
  },
  "displayPreferences": {
    "showOnDesktop": {
      "value": "{{true}}"
    },
    "showOnMobile": {
      "value": "{{false}}"
    },
    "show_on_desktop": {
      "value": "{{true}}"
    },
    "show_on_mobile": {
      "value": "{{false}}"
    }
  },
  "validation": {},
  "layouts": [
    {
      "id": "3a2958da-c160-4bf2-b54f-110ca4b4b0f2",
      "type": "desktop",
      "top": 0,
      "left": 0,
      "width": 0,
      "height": 24,
      "componentId": "dc252ecb-1a7c-4f71-b87e-131ccb40c750",
      "dimensionUnit": "count"
    },
    {
      "id": "fab88310-aa99-4b95-8d84-d6b3ae909c36",
      "type": "mobile",
      "top": 0,
      "left": 0,
      "width": 0,
      "height": 0,
      "componentId": "dc252ecb-1a7c-4f71-b87e-131ccb40c750",
      "dimensionUnit": "count"
    }
  ]
}