{
  "id": "b7941558-ef45-47bd-aa51-17f9377584e3",
  "name": "ModuleContainer",
  "type": "ModuleContainer",
  "pageId": "4d6d0970-08f7-4a79-bd3d-e4fd56aa2a3a",
  "parent": null,
  "properties": {
    "inputItems": {
      "value": []
    },
    "outputItems": {
      "value": []
    },
    "visibility": {
      "value": "{{true}}"
    }
  },
  "general": {},
  "styles": {
    "backgroundColor": {
      "value": "#fff"
    }
  },
  "generalStyles": {},
  "displayPreferences": {
    "showOnDesktop": {
      "value": "{{true}}"
    },
    "showOnMobile": {
      "value": "{{true}}"
    }
  },
  "validation": {},
  "layouts": [
    {
      "id": "2fabfde3-5669-4154-b997-4cebefb8efcc",
      "type": "desktop",
      "top": 50,
      "left": 3,
      "width": 38,
      "height": 400,
      "widthPx": null,
      "fillWidth": null,
      "componentId": "b7941558-ef45-47bd-aa51-17f9377584e3",
      "dimensionUnit": "count"
    },
    {
      "id": "09864cf8-a6ed-4f2c-86b6-49920cc1d653",
      "type": "mobile",
      "top": 50,
      "left": 3,
      "width": 38,
      "height": 400,
      "widthPx": null,
      "fillWidth": null,
      "componentId": "b7941558-ef45-47bd-aa51-17f9377584e3",
      "dimensionUnit": "count"
    }
  ]
}