{
  "id": "333a5314-c248-4ce1-bdd7-8257b7e44c7e",
  "name": "uploadToS3env",
  "options": {
    "method": "PUT",
    "url": "{{page.variables.s3UploadURL}}",
    "headers": [
      [
        "Content-Type",
        "application/octet-stream"
      ]
    ],
    "url_params": [
      [
        "",
        ""
      ]
    ],
    "body": [
      [
        "",
        ""
      ]
    ],
    "cookies": [
      [
        "",
        ""
      ]
    ],
    "json_body": null,
    "body_toggle": true,
    "retry_network_errors": true,
    "transformationLanguage": "javascript",
    "enableTransformation": false,
    "arrayValuesChanged": true,
    "runOnPageLoad": false,
    "raw_body": "{{JSON.stringify( components.0bc8d1ef-847b-46e9-a340-9b5c9de6cc9c.currentTab=== \"t0\" ? components.2ed54798-45ac-468b-9683-dd26f4527054.files[0].base64Data: components.1d4bb366-2ca2-4444-b61c-cec80fd6355a.files[0].base64Data)}}"
  },
  "dataSourceId": "3c96ad36-72c8-4c9e-8a38-59279318063c",
  "appVersionId": "9c996ea9-d6d3-45ea-914d-e69f7520a8b4"
}